viewdom_wired/__init__.py
viewdom_wired/components.py
viewdom_wired/decorators.py
viewdom_wired/field_types.py
viewdom_wired/fixtures.py
viewdom_wired/protocols.py
viewdom_wired/py.typed
viewdom_wired/render.py
viewdom_wired-0.2.0.dist-info/LICENSE.txt
viewdom_wired-0.2.0.dist-info/METADATA
viewdom_wired-0.2.0.dist-info/WHEEL
viewdom_wired-0.2.0.dist-info/top_level.txt
viewdom_wired-0.2.0.dist-info/RECORD
